helloworldjia.py
helloworld_jia-0.0.4.dist-info/LICENSE.txt
helloworld_jia-0.0.4.dist-info/METADATA
helloworld_jia-0.0.4.dist-info/WHEEL
helloworld_jia-0.0.4.dist-info/top_level.txt
helloworld_jia-0.0.4.dist-info/RECORD
