Metadata-Version: 2.1
Name: helloworld-jia
Version: 0.0.4
Summary: Say hello!
Home-page: https://github.com/judy2k/helloworld
Author: Mark Smith
Author-email: mark.smith@vonage.com
License: UNKNOWN
Platform: UNKNOWN
Classifier: Programming Language :: Python :: 3
Classifier: Programming Language :: Python :: 3.6
Classifier: Programming Language :: Python :: 3.7
Classifier: License :: OSI Approved :: GNU General Public License v2 or later (GPLv2+)
Classifier: Operating System :: OS Independent
License-File: LICENSE.txt
Requires-Dist: blessings (~=1.7)
Provides-Extra: dev
Requires-Dist: pytest (>=3.7) ; extra == 'dev'
Requires-Dist: check-manifest ; extra == 'dev'
Requires-Dist: twine ; extra == 'dev'
